u2mcp/.gitignore
u2mcp/__init__.py
u2mcp/__main__.py
u2mcp/_version.py
u2mcp/mcp.py
u2mcp/py.typed
u2mcp/tools/__init__.py
u2mcp/tools/action.py
u2mcp/tools/app.py
u2mcp/tools/device.py
uiautomator2_mcp_server-0.1.2.dist-info/licenses/LICENSE
uiautomator2_mcp_server-0.1.2.dist-info/METADATA
uiautomator2_mcp_server-0.1.2.dist-info/WHEEL
uiautomator2_mcp_server-0.1.2.dist-info/entry_points.txt
uiautomator2_mcp_server-0.1.2.dist-info/top_level.txt
uiautomator2_mcp_server-0.1.2.dist-info/RECORD
