Metadata-Version: 2.4
Name: uiautomator2-mcp-server
Version: 0.1.2
Summary: uiautomator2 mcp server
Author-email: tanbro <tanbro@163.com>
License-Expression: GPL-3.0-or-later
Project-URL: homepage, https://github.com/tanbro/uiautomator2-mcp-server
Project-URL: documentation, https://github.com/tanbro/uiautomator2-mcp-server/blob/main/README.md
Project-URL: repository, https://github.com/tanbro/uiautomator2-mcp-server.git
Project-URL: issues, https://github.com/tanbro/uiautomator2-mcp-server/issues
Project-URL: changelog, https://github.com/tanbro/uiautomator2-mcp-server/blob/main/CHANGELOG.md
Keywords: uiautomator2,mcp,fastmcp,adb,android,adbutils
Classifier: Development Status :: 4 - Beta
Classifier: Programming Language :: Python :: 3
Classifier: Programming Language :: Python :: 3.11
Classifier: Programming Language :: Python :: 3.12
Classifier: Programming Language :: Python :: 3.13
Classifier: Programming Language :: Python :: 3.14
Requires-Python: >=3.11
License-File: LICENSE
Requires-Dist: fastmcp<3.0,>=2.11.0
Requires-Dist: uiautomator2<4.0,>=3.5
Dynamic: license-file
